_opencv.pypy-26.so
opencv_cffi/__init__.py
opencv_cffi/_types.py
opencv_cffi/_version.py
opencv_cffi/build.py
opencv_cffi/core.py
opencv_cffi/gui.py
opencv_cffi/imaging.py
opencv_cffi/object_detection.py
opencv_cffi/utils.py
opencv_cffi/tests/__init__.py
opencv_cffi-0.2.2.dist-info/DESCRIPTION.rst
opencv_cffi-0.2.2.dist-info/METADATA
opencv_cffi-0.2.2.dist-info/RECORD
opencv_cffi-0.2.2.dist-info/WHEEL
opencv_cffi-0.2.2.dist-info/metadata.json
opencv_cffi-0.2.2.dist-info/top_level.txt
