Metadata-Version: 2.0
Name: opencv-cffi
Version: 0.2.2
Summary: A random subset of OpenCV's functionality, wrapped via CFFI
Home-page: https://github.com/Magnetic/opencv-cffi
Author: Magnetic Engineering
Author-email: Engineering@Magnetic.com
License: MIT
Platform: UNKNOWN
Classifier: Development Status :: 3 - Alpha
Classifier: License :: OSI Approved :: MIT License
Classifier: Operating System :: OS Independent
Classifier: Programming Language :: Python
Classifier: Programming Language :: Python :: 2.7
Classifier: Programming Language :: Python :: 2
Classifier: Programming Language :: Python :: Implementation :: CPython
Classifier: Programming Language :: Python :: Implementation :: PyPy
Requires-Dist: betterpath
Requires-Dist: characteristic
